onesocial/__init__.py
onesocial/api.py
onesocial/errors.py
onesocial/oauth.py
onesocial-1.0.1.dist-info/METADATA
onesocial-1.0.1.dist-info/WHEEL
onesocial-1.0.1.dist-info/top_level.txt
onesocial-1.0.1.dist-info/RECORD
